simpledb_dev3-0.3.dist-info/METADATA
simpledb_dev3-0.3.dist-info/RECORD
simpledb_dev3-0.3.dist-info/WHEEL
simpledb_dev3-0.3.dist-info/entry_points.txt
simpledb_dev3-0.3.dist-info/top_level.txt
simpledbdev2/__init__.py
simpledbdev2/__main__.py
simpledbdev2/config.py
simpledbdev2/portalocker.py
simpledbdev2/simpledb_dev.py
simpledbdev2/templates/CreateDomain.xml
simpledbdev2/templates/DeleteAttributes.xml
simpledbdev2/templates/DeleteDomain.xml
simpledbdev2/templates/GetAttributes.xml
simpledbdev2/templates/ListDomains.xml
simpledbdev2/templates/PutAttributes.xml
simpledbdev2/templates/Query.xml
simpledbdev2/templates/QueryWithAttributes.xml
simpledbdev2/templates/__init__.py
simpledbdev2/templates/error.xml
simpledbdev2/tests/__init__.py
