Metadata-Version: 2.1
Name: simpledb-dev3
Version: 0.3
Summary: A local SimpleDB server
Home-page: https://github.com/hovhannes-stdev/simpledb-dev2
Author: Matthew Painter and others
Author-email: hovhannes@stdevmail.com
License: GNU GPL v3
Platform: UNKNOWN
Classifier: Development Status :: 3 - Alpha
Classifier: License :: OSI Approved :: GNU General Public License v3 (GPLv3)
Classifier: Programming Language :: Python :: 3.6
Requires-Dist: pyprelude
Requires-Dist: web.py (==0.40-dev1)
